{
  "sources": {
    "orf_news": {
      "lastSuccessAt": "2026-07-09T19:34:45.899Z",
      "lastFailureAt": null,
      "consecutiveFailures": 0,
      "lastStatus": "ok",
      "lastItemCount": 25
    },
    "orf_oesterreich": {
      "lastSuccessAt": "2026-07-09T19:34:45.872Z",
      "lastFailureAt": null,
      "consecutiveFailures": 0,
      "lastStatus": "ok",
      "lastItemCount": 20
    },
    "orf_burgenland": {
      "lastSuccessAt": "2026-07-09T19:34:46.055Z",
      "lastFailureAt": null,
      "consecutiveFailures": 0,
      "lastStatus": "ok",
      "lastItemCount": 20
    },
    "orf_wien": {
      "lastSuccessAt": "2026-07-09T19:34:45.879Z",
      "lastFailureAt": null,
      "consecutiveFailures": 0,
      "lastStatus": "ok",
      "lastItemCount": 19
    },
    "orf_noe": {
      "lastSuccessAt": "2026-07-09T19:34:45.891Z",
      "lastFailureAt": null,
      "consecutiveFailures": 0,
      "lastStatus": "ok",
      "lastItemCount": 14
    },
    "orf_ooe": {
      "lastSuccessAt": "2026-07-09T19:34:46.079Z",
      "lastFailureAt": null,
      "consecutiveFailures": 0,
      "lastStatus": "ok",
      "lastItemCount": 18
    },
    "orf_salzburg": {
      "lastSuccessAt": "2026-07-09T19:34:46.221Z",
      "lastFailureAt": null,
      "consecutiveFailures": 0,
      "lastStatus": "ok",
      "lastItemCount": 17
    },
    "orf_steiermark": {
      "lastSuccessAt": "2026-07-09T19:34:46.211Z",
      "lastFailureAt": null,
      "consecutiveFailures": 0,
      "lastStatus": "ok",
      "lastItemCount": 19
    },
    "orf_kaernten": {
      "lastSuccessAt": "2026-07-09T19:34:46.414Z",
      "lastFailureAt": null,
      "consecutiveFailures": 0,
      "lastStatus": "ok",
      "lastItemCount": 18
    },
    "orf_tirol": {
      "lastSuccessAt": "2026-07-09T19:34:46.364Z",
      "lastFailureAt": null,
      "consecutiveFailures": 0,
      "lastStatus": "ok",
      "lastItemCount": 18
    },
    "orf_vorarlberg": {
      "lastSuccessAt": "2026-07-09T19:34:46.571Z",
      "lastFailureAt": null,
      "consecutiveFailures": 0,
      "lastStatus": "ok",
      "lastItemCount": 20
    },
    "orf_science": {
      "lastSuccessAt": "2026-07-09T19:34:46.544Z",
      "lastFailureAt": null,
      "consecutiveFailures": 0,
      "lastStatus": "ok",
      "lastItemCount": 17
    },
    "derstandard_newsroom": {
      "lastSuccessAt": "2026-07-09T19:34:46.631Z",
      "lastFailureAt": null,
      "consecutiveFailures": 0,
      "lastStatus": "ok",
      "lastItemCount": 50
    },
    "derstandard_inland": {
      "lastSuccessAt": "2026-07-09T19:34:46.307Z",
      "lastFailureAt": null,
      "consecutiveFailures": 0,
      "lastStatus": "ok",
      "lastItemCount": 32
    },
    "derstandard_international": {
      "lastSuccessAt": "2026-07-09T19:34:47.733Z",
      "lastFailureAt": null,
      "consecutiveFailures": 0,
      "lastStatus": "ok",
      "lastItemCount": 40
    },
    "derstandard_wirtschaft": {
      "lastSuccessAt": "2026-07-09T19:34:46.300Z",
      "lastFailureAt": null,
      "consecutiveFailures": 0,
      "lastStatus": "ok",
      "lastItemCount": 32
    },
    "derstandard_web": {
      "lastSuccessAt": "2026-07-09T19:34:48.459Z",
      "lastFailureAt": null,
      "consecutiveFailures": 0,
      "lastStatus": "ok",
      "lastItemCount": 50
    },
    "derstandard_wissenschaft": {
      "lastSuccessAt": "2026-07-09T19:34:47.285Z",
      "lastFailureAt": null,
      "consecutiveFailures": 0,
      "lastStatus": "ok",
      "lastItemCount": 50
    },
    "derstandard_recht": {
      "lastSuccessAt": "2026-07-09T19:34:47.097Z",
      "lastFailureAt": null,
      "consecutiveFailures": 0,
      "lastStatus": "ok",
      "lastItemCount": 16
    },
    "derstandard_gesundheit": {
      "lastSuccessAt": "2026-07-09T19:34:47.706Z",
      "lastFailureAt": null,
      "consecutiveFailures": 0,
      "lastStatus": "ok",
      "lastItemCount": 16
    },
    "derstandard_panorama": {
      "lastSuccessAt": "2026-07-09T19:34:46.548Z",
      "lastFailureAt": null,
      "consecutiveFailures": 0,
      "lastStatus": "ok",
      "lastItemCount": 42
    },
    "derstandard_live": {
      "lastSuccessAt": "2026-07-09T19:34:48.446Z",
      "lastFailureAt": null,
      "consecutiveFailures": 0,
      "lastStatus": "ok",
      "lastItemCount": 23
    },
    "apa_ots_all": {
      "lastSuccessAt": "2026-07-09T19:34:46.558Z",
      "lastFailureAt": null,
      "consecutiveFailures": 0,
      "lastStatus": "ok",
      "lastItemCount": 15
    },
    "apa_ots_politik": {
      "lastSuccessAt": "2026-07-09T19:34:46.565Z",
      "lastFailureAt": null,
      "consecutiveFailures": 0,
      "lastStatus": "ok",
      "lastItemCount": 15
    },
    "apa_ots_wirtschaft": {
      "lastSuccessAt": "2026-07-09T19:34:46.542Z",
      "lastFailureAt": null,
      "consecutiveFailures": 0,
      "lastStatus": "ok",
      "lastItemCount": 15
    },
    "apa_ots_finanzen": {
      "lastSuccessAt": "2026-07-09T19:34:46.555Z",
      "lastFailureAt": null,
      "consecutiveFailures": 0,
      "lastStatus": "ok",
      "lastItemCount": 15
    },
    "apa_ots_chronik": {
      "lastSuccessAt": "2026-07-09T19:34:46.575Z",
      "lastFailureAt": null,
      "consecutiveFailures": 0,
      "lastStatus": "ok",
      "lastItemCount": 15
    },
    "apa_ots_medien": {
      "lastSuccessAt": "2026-07-09T19:34:46.539Z",
      "lastFailureAt": null,
      "consecutiveFailures": 0,
      "lastStatus": "ok",
      "lastItemCount": 15
    },
    "diepresse_home": {
      "lastSuccessAt": "2026-07-09T19:34:47.598Z",
      "lastFailureAt": null,
      "consecutiveFailures": 0,
      "lastStatus": "ok",
      "lastItemCount": 50
    },
    "diepresse_politik": {
      "lastSuccessAt": "2026-07-09T19:34:47.108Z",
      "lastFailureAt": null,
      "consecutiveFailures": 0,
      "lastStatus": "ok",
      "lastItemCount": 10
    },
    "diepresse_wirtschaft": {
      "lastSuccessAt": "2026-07-09T19:34:47.502Z",
      "lastFailureAt": null,
      "consecutiveFailures": 0,
      "lastStatus": "ok",
      "lastItemCount": 50
    },
    "kurier_home": {
      "lastSuccessAt": "2026-07-09T19:34:47.033Z",
      "lastFailureAt": null,
      "consecutiveFailures": 0,
      "lastStatus": "ok",
      "lastItemCount": 20
    },
    "kurier_politik": {
      "lastSuccessAt": "2026-07-09T19:34:47.027Z",
      "lastFailureAt": null,
      "consecutiveFailures": 0,
      "lastStatus": "ok",
      "lastItemCount": 20
    },
    "kurier_wirtschaft": {
      "lastSuccessAt": "2026-07-09T19:34:47.019Z",
      "lastFailureAt": null,
      "consecutiveFailures": 0,
      "lastStatus": "ok",
      "lastItemCount": 20
    },
    "kurier_chronik": {
      "lastSuccessAt": "2026-07-09T19:34:47.299Z",
      "lastFailureAt": null,
      "consecutiveFailures": 0,
      "lastStatus": "ok",
      "lastItemCount": 20
    },
    "kleinezeitung_home": {
      "lastSuccessAt": "2026-07-09T19:34:49.451Z",
      "lastFailureAt": null,
      "consecutiveFailures": 0,
      "lastStatus": "ok",
      "lastItemCount": 50
    },
    "kleinezeitung_oesterreich": {
      "lastSuccessAt": "2026-07-09T19:34:48.023Z",
      "lastFailureAt": null,
      "consecutiveFailures": 0,
      "lastStatus": "ok",
      "lastItemCount": 50
    },
    "kleinezeitung_politik": {
      "lastSuccessAt": "2026-07-09T19:34:47.326Z",
      "lastFailureAt": null,
      "consecutiveFailures": 0,
      "lastStatus": "ok",
      "lastItemCount": 50
    },
    "kleinezeitung_steiermark": {
      "lastSuccessAt": "2026-07-09T19:34:48.248Z",
      "lastFailureAt": null,
      "consecutiveFailures": 0,
      "lastStatus": "ok",
      "lastItemCount": 34
    },
    "profil_home": {
      "lastSuccessAt": "2026-07-09T19:34:48.469Z",
      "lastFailureAt": null,
      "consecutiveFailures": 0,
      "lastStatus": "ok",
      "lastItemCount": 20
    },
    "profil_oesterreich": {
      "lastSuccessAt": "2026-07-09T19:34:48.478Z",
      "lastFailureAt": null,
      "consecutiveFailures": 0,
      "lastStatus": "ok",
      "lastItemCount": 20
    },
    "profil_gesellschaft": {
      "lastSuccessAt": "2026-07-09T19:34:48.510Z",
      "lastFailureAt": null,
      "consecutiveFailures": 0,
      "lastStatus": "ok",
      "lastItemCount": 20
    }
  }
}
