{
  "version": 1,
  "updatedAt": "2026-07-19T06:18:42.108Z",
  "entries": [
    {
      "clusterId": "cluster-20260719-f6bf0c8e",
      "title": "Bratislava: Tausende bei Regenbogenparade dabei",
      "score": 0.7,
      "items": [
        {
          "itemId": "7964df2a8408feaa9abf04298f2dcf7526884f48207a3a728e6353101514fce4",
          "sourceId": "kurier_home",
          "sourceType": "media",
          "title": "Bratislava: Tausende bei Regenbogenparade dabei",
          "url": "https://kurier.at/chronik/welt/regenbogenparade-bratislava-2026/403176936",
          "summary": "Demonstriert wurde gegen Verschlechterungen für sexuelle Minderheiten.",
          "publishedAt": "2026-07-19T05:45:03.000Z",
          "isNew": true
        },
        {
          "itemId": "c55a63237682b3a1d03ce99531325284f469b9460ead3e878de3014d1b24a0ba",
          "sourceId": "kurier_chronik",
          "sourceType": "media",
          "title": "Bratislava: Tausende bei Regenbogenparade dabei",
          "url": "https://kurier.at/chronik/welt/regenbogenparade-bratislava-2026/403176936",
          "summary": "Demonstriert wurde gegen Verschlechterungen für sexuelle Minderheiten.",
          "publishedAt": "2026-07-19T05:45:03.000Z",
          "isNew": true
        },
        {
          "itemId": "108ff51f3d075ca6c5e50317a6384a013d990e0d41070fd42f0cec0a100d8f3a",
          "sourceId": "orf_news",
          "sourceType": "media",
          "title": "Tausende bei Regenbogenparade in Bratislava",
          "url": "https://orf.at/stories/3436589",
          "isNew": false
        }
      ],
      "queuedAt": "2026-07-19T06:07:24.917Z"
    },
    {
      "clusterId": "cluster-20260719-62dbc7e6",
      "title": "Vierjährige Österreicherin stirbt bei Badeunfall an der Adria",
      "score": 0.7,
      "items": [
        {
          "itemId": "d2502afe5c2e753ab4089b948c4673c6580fd005493636b1946b3e63bf0902cd",
          "sourceId": "kleinezeitung_oesterreich",
          "sourceType": "media",
          "title": "Vierjährige Österreicherin stirbt bei Badeunfall an der Adria",
          "url": "https://www.kleinezeitung.at/artikel/38305281/vierjaehrige-oesterreicherin-stirbt-bei-badeunfall-an-der-adria",
          "summary": "Jugendliche fanden das Mädchen regungslos im Pool einer Hotelanlage. Rettungskräfte versuchten vergeblich das Kind zu reanimieren.",
          "publishedAt": "2026-07-19T05:57:42.000Z",
          "isNew": true
        },
        {
          "itemId": "a2832da73fa027ffd9b39ebeba56dc232f6d6dcec3b92058c2463f0fd14abe44",
          "sourceId": "derstandard_newsroom",
          "sourceType": "media",
          "title": "Vierjährige aus Österreich verstirbt nach Badeunfall an der Adria",
          "url": "https://www.derstandard.at/story/3000000332026/vierj228hrige-214sterreicherin-verstirbt-nach-badeunfall-an-der-adria",
          "isNew": false
        },
        {
          "itemId": "5cb59d7d7fee59745bb9be0a70ff0fa035ce96df9b8b0e1c39360eb680a8cd83",
          "sourceId": "derstandard_panorama",
          "sourceType": "media",
          "title": "Vierjährige aus Österreich verstirbt nach Badeunfall an der Adria",
          "url": "https://www.derstandard.at/story/3000000332026/vierj228hrige-214sterreicherin-verstirbt-nach-badeunfall-an-der-adria",
          "isNew": false
        }
      ],
      "queuedAt": "2026-07-19T06:07:24.917Z"
    },
    {
      "clusterId": "cluster-20260719-6ee5d55f",
      "title": "Schweres Erdbeben erschütterte Peru: Ein Toter",
      "score": 0.7,
      "items": [
        {
          "itemId": "6c27b333d00f9704e18235398014f396cb5cc7f4b594aee16b4d0e51901094e4",
          "sourceId": "orf_news",
          "sourceType": "media",
          "title": "Schweres Erdbeben erschütterte Peru: Ein Toter",
          "url": "https://orf.at/stories/3436599",
          "publishedAt": "2026-07-19T05:35:19.000Z",
          "isNew": true
        },
        {
          "itemId": "109a3c722283d424a17ef499a07b8df0d658fb0aad901fa1f5f637ef7d2aaab7",
          "sourceId": "diepresse_home",
          "sourceType": "media",
          "title": "Schweres Erdbeben erschüttert Südwesten von Peru",
          "url": "https://www.diepresse.com/38304965/schweres-erdbeben-erschuettert-suedwesten-von-peru",
          "summary": "Mehrere Gebäude sind eingestürzt, mindestens eine Person kam ums Leben.",
          "publishedAt": "2026-07-19T05:38:51.000Z",
          "isNew": true
        }
      ],
      "queuedAt": "2026-07-19T06:07:24.917Z"
    },
    {
      "clusterId": "cluster-20260719-58d49b78",
      "title": "Mindestens ein Toter bei heftigem Angriff auf Kiew",
      "score": 0.7,
      "items": [
        {
          "itemId": "295e4bd15bdba624a223d0df7e497fc04be9196fed5b57732bded5b28dbd8cd2",
          "sourceId": "orf_news",
          "sourceType": "media",
          "title": "Mindestens ein Toter bei heftigem Angriff auf Kiew",
          "url": "https://orf.at/stories/3436597",
          "publishedAt": "2026-07-19T05:25:06.000Z",
          "isNew": true
        },
        {
          "itemId": "c4c8e7684744a6a7f83acdbb6d001387649d1d78e5b55d94439be3c5050cfe28",
          "sourceId": "derstandard_newsroom",
          "sourceType": "media",
          "title": "Mindestens ein Toter bei russischem Angriff auf Kyjiw",
          "url": "https://www.derstandard.at/jetzt/livebericht/3000000332010/mindestens-ein-toter-bei-russischem-angriff-auf-kyjiw",
          "summary": "Proteste gegen die Entlassung von Verteidigungsminister Fedorow halten an. Der ukrainische Präsident Selenskyj verspricht Demonstranten Entscheidungen zur Armee",
          "publishedAt": "2026-07-19T05:17:34.000Z",
          "isNew": true
        },
        {
          "itemId": "d7d41e8c18863b4ecf8e0d4bfcca47d3d46cb05adfe7a5238f72242400cd2f57",
          "sourceId": "derstandard_international",
          "sourceType": "media",
          "title": "Mindestens ein Toter bei russischem Angriff auf Kyjiw",
          "url": "https://www.derstandard.at/jetzt/livebericht/3000000332010/mindestens-ein-toter-bei-russischem-angriff-auf-kyjiw",
          "summary": "Proteste gegen die Entlassung von Verteidigungsminister Fedorow halten an. Der ukrainische Präsident Selenskyj verspricht Demonstranten Entscheidungen zur Armee",
          "publishedAt": "2026-07-19T05:17:34.000Z",
          "isNew": true
        },
        {
          "itemId": "328512860f8654adfdc87f6e9fd8c009b2becbb4fb394a4860dcbcb56acb5298",
          "sourceId": "derstandard_live",
          "sourceType": "media",
          "title": "Mindestens ein Toter bei russischem Angriff auf Kyjiw",
          "url": "https://www.derstandard.at/jetzt/livebericht/3000000332010/mindestens-ein-toter-bei-russischem-angriff-auf-kyjiw",
          "summary": "Proteste gegen die Entlassung von Verteidigungsminister Fedorow halten an. Der ukrainische Präsident Selenskyj verspricht Demonstranten Entscheidungen zur Armee",
          "publishedAt": "2026-07-19T05:17:34.000Z",
          "isNew": true
        }
      ],
      "queuedAt": "2026-07-19T06:07:24.917Z"
    },
    {
      "clusterId": "cluster-20260719-b785aea4",
      "title": "Nach Tod zweier US-Soldaten: Neue US-Angriffe auf Iran",
      "score": 0.7,
      "items": [
        {
          "itemId": "a55d0a3d36a0657b8c339783b4189bc09813be9811cac7ae9347e23a493eb9a7",
          "sourceId": "orf_news",
          "sourceType": "media",
          "title": "Nach Tod zweier US-Soldaten: Neue US-Angriffe auf Iran",
          "url": "https://orf.at/stories/3436596",
          "publishedAt": "2026-07-19T05:20:45.000Z",
          "isNew": true
        },
        {
          "itemId": "3cefa44abb63c9b493948dfb9fe678f6dce76e5d372479ba6b35a363c8250be9",
          "sourceId": "derstandard_newsroom",
          "sourceType": "media",
          "title": "Nach Tod von US-Soldaten und nächtelangen Angriffen: USA und Iran schwören einander Rache",
          "url": "https://www.derstandard.at/story/3000000332028/nach-tod-von-us-soldaten-und-naechtelangen-angriffen-usa-und-iran-schwoeren-einander-rache",
          "summary": "Irans Vizeaußenminister erklärte, man habe das mit den USA vereinbarte Rahmenabkommen ausgesetzt und fühle sich nicht mehr daran gebunden. Trump sagt, das sei ihm \"völlig egal\"",
          "publishedAt": "2026-07-19T05:43:27.000Z",
          "isNew": true
        },
        {
          "itemId": "094afa342789b35688a0098b6455b9472a00fc081fb3f2f05924f5071281615a",
          "sourceId": "derstandard_international",
          "sourceType": "media",
          "title": "Nach Tod von US-Soldaten und nächtelangen Angriffen: USA und Iran schwören einander Rache",
          "url": "https://www.derstandard.at/story/3000000332028/nach-tod-von-us-soldaten-und-naechtelangen-angriffen-usa-und-iran-schwoeren-einander-rache",
          "summary": "Irans Vizeaußenminister erklärte, man habe das mit den USA vereinbarte Rahmenabkommen ausgesetzt und fühle sich nicht mehr daran gebunden. Trump sagt, das sei ihm \"völlig egal\"",
          "publishedAt": "2026-07-19T05:43:27.000Z",
          "isNew": true
        },
        {
          "itemId": "9c1a8760bf8a3d57eb567b74d3525c3bb057dc7229dca9814898b812843acca7",
          "sourceId": "derstandard_international",
          "sourceType": "media",
          "title": "USA erhöhen mit neuen Angriffen und Drohungen Druck auf Iran",
          "url": "https://www.derstandard.at/story/3000000331671/usa-erhoehen-mit-neuen-angriffen-und-drohungen-druck-auf-iran",
          "isNew": false
        }
      ],
      "queuedAt": "2026-07-19T06:07:24.917Z"
    },
    {
      "clusterId": "cluster-20260719-e4b71355",
      "title": "Kleinere Wohnungen senken Emissionen",
      "score": 0.7,
      "items": [
        {
          "itemId": "0220f6ec44fb803e9785dd9d661c999102d9e21568037372853c8b5b78a5548a",
          "sourceId": "orf_oesterreich",
          "sourceType": "media",
          "title": "Kleinere Wohnungen senken Emissionen",
          "url": "https://steiermark.orf.at/stories/3363259",
          "summary": "Der Gebäudesektor trägt erheblich zu den Treibhausgasemissionen in Europa bei. Eine internationale Studie, an der auch die TU-Graz beteiligt war, untersuchte mögliche Strategien zur Reduzierung dieser Emissionen. Ein Ergebnis: Emissionen könnten bis 2050 um 90 Prozent reduziert werden.",
          "publishedAt": "2026-07-19T05:45:00.000Z",
          "isNew": true
        },
        {
          "itemId": "ec91957655bff3d7ddffd2ed59254cfe69bdbafd8e4b7c4f1ad9e3267db25d7b",
          "sourceId": "orf_steiermark",
          "sourceType": "media",
          "title": "Kleinere Wohnungen senken Emissionen",
          "url": "https://steiermark.orf.at/stories/3363259",
          "summary": "Der Gebäudesektor trägt erheblich zu den Treibhausgasemissionen in Europa bei. Eine internationale Studie, an der auch die TU-Graz beteiligt war, untersuchte mögliche Strategien zur Reduzierung dieser Emissionen. Ein Ergebnis: Emissionen könnten bis 2050 um 90 Prozent reduziert werden.",
          "publishedAt": "2026-07-19T05:45:00.000Z",
          "isNew": true
        }
      ],
      "queuedAt": "2026-07-19T06:07:24.917Z"
    },
    {
      "clusterId": "cluster-20260719-a72dc86a",
      "title": "Gut Aiderbichl: Teamarbeit mit Veterinär-Uni Wien",
      "score": 0.65,
      "items": [
        {
          "itemId": "1e397c113f48ab4904758dcb3e9056f2c1a0f780804daf40a6ebf4efb511d9ef",
          "sourceId": "orf_oesterreich",
          "sourceType": "media",
          "title": "Gut Aiderbichl: Teamarbeit mit Veterinär-Uni Wien",
          "url": "https://salzburg.orf.at/stories/3363270",
          "summary": "25 Jahre nach Gründung von Gut Aiderbichl in Henndorf (Flachgau) arbeitet der Gnadenhof künftig mit der Veterinärmedizinschen Universität Wien eng zusammen. Studenten kommen turnusweise nach Salzburg, um praktische Erfahrung zu sammeln.",
          "publishedAt": "2026-07-19T06:00:00.000Z",
          "isNew": true
        }
      ],
      "queuedAt": "2026-07-19T06:07:24.917Z"
    },
    {
      "clusterId": "cluster-20260719-e791a0c9",
      "title": "Klettersteig-Tour im Kleinwalsertal endet tödlich",
      "score": 0.65,
      "items": [
        {
          "itemId": "e24de305474f90afb8302a142f41157a78267937f6c9e439b818093b2481aefa",
          "sourceId": "orf_oesterreich",
          "sourceType": "media",
          "title": "Klettersteig-Tour im Kleinwalsertal endet tödlich",
          "url": "https://vorarlberg.orf.at/stories/3363295",
          "summary": "Im Kleinwalsertal ist am Samstag ein deutscher Urlauber tödlich verunglückt. Er war auf dem Mindelheimer Klettersteig unterwegs – und offenbar war der Mann schon erschöpft. Er soll das Gleichgewicht verloren haben und sei dabei abgestürzt, berichtet die Polizei.",
          "publishedAt": "2026-07-19T04:58:55.000Z",
          "isNew": true
        },
        {
          "itemId": "9da42a1f59528e155fa1613bad03e4b430b52f02eeb9d137e0f99e23573d56d9",
          "sourceId": "orf_vorarlberg",
          "sourceType": "media",
          "title": "Klettersteig-Tour im Kleinwalsertal endet tödlich",
          "url": "https://vorarlberg.orf.at/stories/3363295",
          "summary": "Im Kleinwalsertal ist am Samstag ein deutscher Urlauber tödlich verunglückt. Er war auf dem Mindelheimer Klettersteig unterwegs – und offenbar war der Mann schon erschöpft. Er soll das Gleichgewicht verloren haben und sei dabei abgestürzt, berichtet die Polizei.",
          "publishedAt": "2026-07-19T04:58:55.000Z",
          "isNew": true
        }
      ],
      "queuedAt": "2026-07-19T06:07:24.917Z"
    },
    {
      "clusterId": "cluster-20260719-939f85c4",
      "title": "Rechtsstreit um Edelbordell in Kitzbühel",
      "score": 0.65,
      "items": [
        {
          "itemId": "360343e7ff6c90e8a92d317ba8b9e490cc1a838e9037449c451d44c67a47b635",
          "sourceId": "orf_oesterreich",
          "sourceType": "media",
          "title": "Rechtsstreit um Edelbordell in Kitzbühel",
          "url": "https://tirol.orf.at/stories/3363188",
          "summary": "In Kitzbühel schwelt zwischen der Stadt und einer Gesellschaft seit Jahren ein Rechtsstreit um ein geplantes Edelbordell. Nach Niederlagen vor Gericht verhängte die Stadt zunächst eine Bausperre. Nun hat sie das Grundstück trotz des noch offenen Bauansuchens umgewidmet. Der Bauwerber kündigt an, „alle rechtlichen Mittel“ auszuschöpfen.",
          "publishedAt": "2026-07-19T04:06:00.000Z",
          "isNew": true
        },
        {
          "itemId": "d6e07ecc359ba923599acdfe23fd27c518c82e37cac1e3147ca2f2ee79ed8976",
          "sourceId": "orf_tirol",
          "sourceType": "media",
          "title": "Rechtsstreit um Edelbordell in Kitzbühel",
          "url": "https://tirol.orf.at/stories/3363188",
          "summary": "In Kitzbühel schwelt zwischen der Stadt und einer Gesellschaft seit Jahren ein Rechtsstreit um ein geplantes Edelbordell. Nach Niederlagen vor Gericht verhängte die Stadt zunächst eine Bausperre. Nun hat sie das Grundstück trotz des noch offenen Bauansuchens umgewidmet. Der Bauwerber kündigt an, „alle rechtlichen Mittel“ auszuschöpfen.",
          "publishedAt": "2026-07-19T04:06:00.000Z",
          "isNew": true
        }
      ],
      "queuedAt": "2026-07-19T06:07:24.917Z"
    },
    {
      "clusterId": "cluster-20260718-ff355389",
      "title": "Mamdani prüft Festnahme Netanjahus bei UNO-Generaldebatte",
      "score": 0.65,
      "items": [
        {
          "itemId": "1f9b271aedce1e4f7946ababd554bc369d280e0c4aca84bef5195157ff839260",
          "sourceId": "orf_news",
          "sourceType": "media",
          "title": "Mamdani prüft Festnahme Netanjahus bei UNO-Generaldebatte",
          "url": "https://orf.at/stories/3436588",
          "publishedAt": "2026-07-18T20:03:15.000Z",
          "isNew": true
        }
      ],
      "queuedAt": "2026-07-18T20:07:25.006Z"
    },
    {
      "clusterId": "cluster-20260718-43ebcce7",
      "title": "Präsident unterzeichnet Ende seiner Amtszeit",
      "score": 0.65,
      "items": [
        {
          "itemId": "c4dfbeca8e6a8de8ef727334501fcc76bece7b4b8ac580e3d12cd1348ad451b8",
          "sourceId": "orf_news",
          "sourceType": "media",
          "title": "Präsident unterzeichnet Ende seiner Amtszeit",
          "url": "https://orf.at/stories/3436581",
          "summary": "Fünf Tage hat das ungarische Parlament dem Staatspräsidenten Tamas Sulyok Zeit gegeben, eine beschlossene Verfassungsänderung zu unterzeichnen. Danach hätte das Parlament ein Amtsenthebungsverfahren eingeleitet. Dem ist Sulyok nun zuvorgekommen. Am fünften Tag dieser Frist unterzeichnete er am Samstag die Verfassungsänderung. Damit beendete er zugleich seine Amtszeit als Präsident mit sofortiger Wirkung.",
          "publishedAt": "2026-07-18T18:50:19.000Z",
          "isNew": true
        }
      ],
      "queuedAt": "2026-07-18T20:07:25.006Z"
    }
  ]
}
